{"cameraMode":{"drawMode":0,"name":"Shaded","section":"Shading Mode"},"sceneLighting":true,"audioPlay":false,"sceneViewState":{"m_AlwaysRefresh":false,"showFog":true,"showSkybox":true,"showFlares":true,"showImageEffects":true,"showParticleSystems":true,"showVisualEffectGraphs":true,"m_FxEnabled":true},"in2DMode":false,"pivot":{"x":196.54183959960938,"y":-8.06771183013916,"z":342.5328063964844},"rotation":{"x":-0.04510464146733284,"y":0.8005460500717163,"z":-0.06323318928480149,"w":-0.5948076844215393},"size":92.70657348632813,"orthographic":false}